zaleycash/__init__.py
zaleycash/client.py
zaleycash/error_codes.py
zaleycash/exceptions.py
python_zaleycash-0.1.1.dist-info/LICENSE.md
python_zaleycash-0.1.1.dist-info/METADATA
python_zaleycash-0.1.1.dist-info/WHEEL
python_zaleycash-0.1.1.dist-info/top_level.txt
python_zaleycash-0.1.1.dist-info/RECORD
